{"method_name":"build_query","expected_type_hint":4,"name":"Builder Pattern DE","description":"Implementiere ein SQL Query Builder Pattern. Gegeben Operationen wie ['select', 'name,age'], ['from', 'users'], ['where', 'age > 18'], ['orderby', 'name'], baue einen SQL-Query-String. Gib die komplette Query zurueck.","hints":"Baue die Query Schritt fuer Schritt, fuege jede Klausel an. Das Builder Pattern trennt Konstruktion von Repraesentation.","language":"DE","difficulty":8,"arguments":[{"name":"operations","type_hint":28}],"tests":[{"expected":"SELECT name FROM users","name":"Einfach","description":"select + from","arguments":[[["select","name"],["from","users"]]]},{"expected":"SELECT * FROM users WHERE age > 18","name":"Mit Where","description":"select + from + where","arguments":[[["select","*"],["from","users"],["where","age > 18"]]]},{"expected":"SELECT name, age FROM users WHERE active = 1 ORDER BY name","name":"Komplett","description":"alle Klauseln","arguments":[[["select","name, age"],["from","users"],["where","active = 1"],["orderby","name"]]]},{"expected":"SELECT * FROM products ORDER BY price","name":"Ohne Where","description":"ohne where Klausel","arguments":[[["select","*"],["from","products"],["orderby","price"]]]}]}
