{"method_name":"word_break","expected_type_hint":1,"name":"Word Break","description":"Given a string and a dictionary of words, determine if the string can be segmented into space-separated words from the dictionary.","hints":"Use dynamic programming. dp[i] is true if s[0:i] can be segmented. For each position, check all possible word endings.","language":"EN","difficulty":6,"arguments":[{"name":"s","type_hint":4},{"name":"word_dict","type_hint":28}],"tests":[{"expected":true,"name":"Leetcode","description":"'leetcode', ['leet','code'] -> true","arguments":["leetcode",["leet","code"]]},{"expected":true,"name":"Applepenapple","description":"'applepenapple', ['apple','pen'] -> true","arguments":["applepenapple",["apple","pen"]]},{"expected":false,"name":"Catsandog","description":"'catsandog', ['cats','dog','sand','and','cat'] -> false","arguments":["catsandog",["cats","dog","sand","and","cat"]]},{"expected":true,"name":"Empty string","description":"'', ['a'] -> true","arguments":["",["a"]]}]}
